glue_helper_lib/__init__.py
glue_helper_lib/arguments.py
glue_helper_lib/hudi/__init__.py
glue_helper_lib/hudi/config.py
glue_helper_lib/hudi/session.py
glue_helper_lib/hudi/table.py
glue_helper_lib/logging.py
glue_helper_lib/session.py
glue_helper_lib/table.py
glue_helper_lib-0.5.5.dist-info/LICENSE
glue_helper_lib-0.5.5.dist-info/METADATA
glue_helper_lib-0.5.5.dist-info/WHEEL
glue_helper_lib-0.5.5.dist-info/RECORD
